{
    "EssentialRepo": [
        {
            "sourceType":"LOCAL_FS",
            "path": "~/Workspaces/meta-platform-repo/repos/essential-repository"
        },
        {
            "sourceType":"GITHUB_RELEASE",
            "repositoryName":"essential-repository",
            "repositoryOwner": "Meta-Platform"
        },
        {
            "sourceType":"GITHUB_REPO"
        },
        {
            "sourceType":"GOOGLE_DRIVE",
            "fileId": "12PKZU1Uea1yYnhO7R26Il9eyF__v6MAc"
        }
    ],
    "EcosystemCoreRepo": [
        {
            "sourceType":"LOCAL_FS",
            "path": "~/Workspaces/meta-platform-repo/repos/ecosystem-core-repository"
        },
        {
            "sourceType":"GITHUB_RELEASE",
            "repositoryName":"ecosystem-core-repository",
            "repositoryOwner": "Meta-Platform"
        },
        {
            "sourceType":"GITHUB_REPO"
        },
        {
            "sourceType":"GOOGLE_DRIVE",
            "fileId": "1-PuPdjU36acGmoPgusYWrMuhyGyMnoRI"
        }
    ],
    "PlaformApplicationsRepo": [
        {
            "sourceType":"LOCAL_FS",
            "path": "~/Workspaces/meta-platform-repo/repos/applications-repository"
        }
    ]
}